google_fonts/__init__.py
google_fonts/cli.py
google_fonts/font/__init__.py
google_fonts/font/install.py
google_fonts/font/list.py
google_fonts/google_fonts.py
google_fonts/utils/__init__.py
google_fonts/utils/font_data.py
google_fonts-0.1.8.dist-info/METADATA
google_fonts-0.1.8.dist-info/WHEEL
google_fonts-0.1.8.dist-info/entry_points.txt
google_fonts-0.1.8.dist-info/RECORD
